premlike/PREM.py
premlike/__init__.py
premlike/const.py
premlike/earth_model.py
premlike/peice_poly.py
premlike/physics.py
premlike-0.1.0a2.dist-info/licenses/LICENSE
premlike-0.1.0a2.dist-info/METADATA
premlike-0.1.0a2.dist-info/WHEEL
premlike-0.1.0a2.dist-info/top_level.txt
premlike-0.1.0a2.dist-info/RECORD
